lanpartydb/__init__.py
lanpartydb/deserialization.py
lanpartydb/models.py
lanpartydb/py.typed
lanpartydb/serialization.py
lanpartydb-0.11.1.dist-info/METADATA
lanpartydb-0.11.1.dist-info/WHEEL
lanpartydb-0.11.1.dist-info/licenses/LICENSE
lanpartydb-0.11.1.dist-info/RECORD
