Metadata-Version: 2.4
Name: lanpartydb
Version: 0.11.1
Summary: Python library for the OrgaTalk LAN Party Database
Project-URL: Repository, https://github.com/lanpartydb/lib-python
Project-URL: Changelog, https://github.com/lanpartydb/lib-python/blob/main/CHANGELOG.md
Author-email: Jochen Kupperschmidt <homework@nwsnet.de>
License: MIT
License-File: LICENSE
Keywords: lanparty
Classifier: Intended Audience :: Developers
Classifier: License :: OSI Approved :: MIT License
Classifier: Programming Language :: Python :: 3.11
Classifier: Programming Language :: Python :: 3.12
Classifier: Programming Language :: Python :: 3.13
Requires-Python: >=3.11
Requires-Dist: tomlkit>=0.13.3
